telegram_markdown_converter/__init__.py
telegram_markdown_converter/converter.py
telegram_markdown_converter-1.0.5.dist-info/licenses/LICENSE
telegram_markdown_converter-1.0.5.dist-info/METADATA
telegram_markdown_converter-1.0.5.dist-info/WHEEL
telegram_markdown_converter-1.0.5.dist-info/top_level.txt
telegram_markdown_converter-1.0.5.dist-info/RECORD
