Metadata-Version: 2.4
Name: telegram-markdown-converter
Version: 1.0.5
Summary: A Python library for converting Markdown to Telegram-safe MarkdownV2 formatting
Author-email: Evan Boulatoff <ngoldo@gmail.com>
License: MIT
Project-URL: Homepage, https://github.com/ngoldo/telegram-markdown-converter
Project-URL: Repository, https://github.com/ngoldo/telegram-markdown-converter
Project-URL: Issues, https://github.com/ngoldo/telegram-markdown-converter/issues
Project-URL: Documentation, https://github.com/ngoldo/telegram-markdown-converter#readme
Keywords: telegram,markdown,converter,formatting,markdownv2
Classifier: Development Status :: 5 - Production/Stable
Classifier: Intended Audience :: Developers
Classifier: License :: OSI Approved :: MIT License
Classifier: Programming Language :: Python :: 3
Classifier: Programming Language :: Python :: 3.10
Classifier: Programming Language :: Python :: 3.11
Classifier: Programming Language :: Python :: 3.12
Classifier: Programming Language :: Python :: 3.13
Classifier: Topic :: Communications :: Chat
Classifier: Topic :: Text Processing :: Markup
Classifier: Topic :: Software Development :: Libraries :: Python Modules
Requires-Python: >=3.10
License-File: LICENSE
Provides-Extra: dev
Requires-Dist: pytest>=7.0.0; extra == "dev"
Requires-Dist: pytest-cov>=4.0.0; extra == "dev"
Requires-Dist: black>=23.0.0; extra == "dev"
Requires-Dist: isort>=5.12.0; extra == "dev"
Requires-Dist: flake8>=6.0.0; extra == "dev"
Requires-Dist: mypy>=1.0.0; extra == "dev"
Requires-Dist: pre-commit>=3.0.0; extra == "dev"
Provides-Extra: test
Requires-Dist: pytest>=7.0.0; extra == "test"
Requires-Dist: pytest-cov>=4.0.0; extra == "test"
Dynamic: license-file
